quickmathsfunctions.py
quickmathsfunctions-0.0.3.dist-info/LICENSE
quickmathsfunctions-0.0.3.dist-info/METADATA
quickmathsfunctions-0.0.3.dist-info/WHEEL
quickmathsfunctions-0.0.3.dist-info/top_level.txt
quickmathsfunctions-0.0.3.dist-info/RECORD
