Metadata-Version: 2.1
Name: quickmathsfunctions
Version: 0.0.3
Summary: A simple test package for Buildkite's Python CI/CD demonstration
Author: Ravgeet Dhillon
Classifier: Programming Language :: Python :: 3
Classifier: License :: OSI Approved :: MIT License
Classifier: Operating System :: OS Independent
Requires-Python: >=3.6
License-File: LICENSE
